{
  "id": 8434,
  "frameLengths": [
    4,
    4,
    4,
    4,
    5,
    5,
    5,
    5,
    5,
    5,
    4,
    4,
    4,
    4,
    4,
    4,
    4,
    4,
    4,
    4,
    4
  ],
  "frameIDs": [
    153354241,
    153354242,
    153354243,
    153354244,
    153354245,
    153354246,
    153354247,
    153354248,
    153354249,
    153354250,
    153354251,
    153354252,
    153354253,
    153354254,
    153354255,
    153354256,
    153354257,
    153354258,
    153354259,
    153354260,
    153354261
  ],
  "frameStep": -1,
  "interleaveLeave": [],
  "stretches": false,
  "forcedPriority": 6,
  "leftHandItem": -1,
  "rightHandItem": -1,
  "maxLoops": 99,
  "precedenceAnimating": -1,
  "priority": -1,
  "replyMode": 2,
  "chatFrameIds": [],
  "frameSounds": [
    null,
    {
      "id": 4188,
      "loops": 1,
      "location": 15,
      "retain": 0,
      "weight": 100
    }
  ],
  "animMayaID": -1,
  "animMayaMasks": []
}