{
  "id": 37962,
  "translation": {
    "x": 0,
    "y": 0,
    "z": 0
  },
  "rotation": {
    "x": 0,
    "y": 0,
    "z": 0
  },
  "vertexCount": 98,
  "faceCount": 196,
  "numTextureFaces": 0,
  "vertexPositionsX": [
    -54,
    -54,
    -40,
    -40,
    -45,
    -45,
    -38,
    -38,
    -42,
    -42,
    -40,
    -38,
    -38,
    -40,
    -37,
    -37,
    -39,
    -36,
    -35,
    -40,
    -39,
    -41,
    -39,
    -33,
    -33,
    -39,
    -35,
    -35,
    -37,
    -33,
    -31,
    -37,
    -33,
    -38,
    -31,
    -30,
    -27,
    -31,
    -27,
    -25,
    -30,
    -31,
    -36,
    -38,
    -43,
    -46,
    -42,
    -36,
    -29,
    -29,
    -26,
    -25,
    -22,
    -28,
    -32,
    -32,
    -22,
    -20,
    -19,
    -19,
    -20,
    -18,
    -21,
    -26,
    -42,
    -40,
    -28,
    -16,
    -15,
    -11,
    -16,
    -14,
    -41,
    -41,
    -34,
    -30,
    -43,
    -48,
    -51,
    -53,
    -47,
    -44,
    -42,
    -35,
    -20,
    -22,
    -30,
    -41,
    -42,
    -46,
    -34,
    -26,
    52,
    49,
    49,
    51,
    -9,
    -21
  ],
  "vertexPositionsY": [
    1,
    0,
    0,
    1,
    1,
    0,
    -1,
    0,
    0,
    -1,
    -1,
    -1,
    0,
    0,
    -1,
    0,
    -1,
    -1,
    1,
    1,
    0,
    -1,
    -1,
    -1,
    2,
    2,
    -1,
    1,
    -1,
    -1,
    -1,
    1,
    0,
    -1,
    -1,
    -1,
    -1,
    0,
    0,
    1,
    1,
    1,
    1,
    0,
    -1,
    -1,
    -1,
    -1,
    1,
    0,
    0,
    -1,
    -1,
    -1,
    -1,
    1,
    0,
    1,
    1,
    -1,
    -1,
    0,
    0,
    0,
    0,
    0,
    1,
    1,
    0,
    0,
    -1,
    0,
    0,
    -1,
    -1,
    -1,
    1,
    0,
    0,
    0,
    0,
    0,
    0,
    0,
    0,
    0,
    1,
    1,
    0,
    1,
    1,
    1,
    0,
    0,
    -1,
    -1,
    0,
    0
  ],
  "vertexPositionsZ": [
    56,
    56,
    45,
    45,
    40,
    40,
    43,
    43,
    39,
    39,
    37,
    41,
    41,
    38,
    40,
    40,
    37,
    41,
    40,
    35,
    38,
    35,
    35,
    38,
    38,
    35,
    38,
    38,
    36,
    31,
    33,
    36,
    31,
    27,
    30,
    32,
    37,
    33,
    37,
    34,
    32,
    30,
    25,
    27,
    32,
    30,
    22,
    25,
    27,
    27,
    29,
    34,
    41,
    46,
    43,
    43,
    41,
    39,
    29,
    29,
    39,
    40,
    43,
    47,
    52,
    48,
    46,
    33,
    21,
    18,
    33,
    34,
    53,
    20,
    16,
    20,
    32,
    41,
    44,
    43,
    28,
    21,
    19,
    15,
    10,
    14,
    20,
    20,
    22,
    30,
    16,
    29,
    -58,
    -60,
    -59,
    -58,
    19,
    9
  ],
  "faceVertexIndices1": [
    0,
    0,
    0,
    0,
    0,
    1,
    2,
    2,
    3,
    3,
    4,
    4,
    4,
    5,
    6,
    6,
    6,
    7,
    7,
    7,
    8,
    8,
    14,
    14,
    14,
    14,
    14,
    15,
    15,
    15,
    15,
    12,
    13,
    13,
    10,
    17,
    17,
    17,
    17,
    18,
    18,
    18,
    19,
    19,
    19,
    20,
    26,
    26,
    26,
    26,
    26,
    26,
    26,
    28,
    28,
    29,
    29,
    29,
    29,
    29,
    30,
    30,
    30,
    27,
    27,
    27,
    27,
    36,
    37,
    37,
    37,
    37,
    32,
    32,
    32,
    33,
    33,
    33,
    33,
    33,
    34,
    34,
    34,
    34,
    35,
    35,
    35,
    35,
    36,
    36,
    36,
    36,
    38,
    38,
    38,
    39,
    39,
    39,
    39,
    39,
    51,
    36,
    52,
    52,
    52,
    52,
    53,
    53,
    53,
    54,
    54,
    55,
    55,
    56,
    56,
    56,
    57,
    57,
    57,
    58,
    58,
    59,
    59,
    59,
    51,
    60,
    60,
    61,
    67,
    67,
    65,
    66,
    66,
    63,
    28,
    28,
    23,
    46,
    47,
    47,
    47,
    47,
    42,
    43,
    44,
    44,
    44,
    44,
    45,
    45,
    45,
    46,
    46,
    73,
    73,
    74,
    74,
    74,
    75,
    75,
    75,
    42,
    42,
    42,
    43,
    76,
    76,
    77,
    78,
    78,
    86,
    87,
    87,
    87,
    88,
    88,
    89,
    85,
    85,
    50,
    40,
    41,
    48,
    48,
    48,
    49,
    49,
    50,
    50,
    91,
    96,
    96,
    96,
    97,
    97,
    97
  ],
  "faceVertexIndices2": [
    1,
    2,
    3,
    4,
    5,
    5,
    5,
    6,
    6,
    7,
    7,
    8,
    9,
    9,
    9,
    10,
    11,
    11,
    12,
    13,
    13,
    10,
    15,
    12,
    11,
    16,
    17,
    17,
    18,
    19,
    20,
    20,
    20,
    16,
    16,
    16,
    21,
    22,
    23,
    23,
    24,
    25,
    25,
    22,
    21,
    21,
    27,
    24,
    23,
    28,
    29,
    30,
    27,
    27,
    31,
    31,
    32,
    33,
    34,
    35,
    35,
    36,
    37,
    37,
    32,
    31,
    25,
    38,
    38,
    39,
    40,
    41,
    41,
    42,
    43,
    43,
    44,
    45,
    46,
    47,
    47,
    41,
    48,
    49,
    49,
    50,
    40,
    51,
    51,
    52,
    53,
    54,
    54,
    55,
    56,
    56,
    57,
    58,
    59,
    51,
    39,
    39,
    51,
    60,
    61,
    62,
    62,
    63,
    64,
    64,
    65,
    65,
    66,
    66,
    63,
    62,
    62,
    61,
    67,
    67,
    68,
    68,
    69,
    70,
    70,
    70,
    71,
    71,
    71,
    69,
    64,
    64,
    72,
    72,
    22,
    25,
    22,
    73,
    73,
    74,
    75,
    42,
    47,
    47,
    43,
    76,
    77,
    78,
    78,
    79,
    80,
    80,
    81,
    81,
    82,
    82,
    83,
    84,
    84,
    85,
    86,
    86,
    87,
    88,
    88,
    88,
    89,
    89,
    89,
    80,
    90,
    90,
    83,
    82,
    82,
    81,
    81,
    84,
    90,
    91,
    91,
    91,
    91,
    92,
    93,
    93,
    94,
    94,
    95,
    95,
    71,
    70,
    69,
    83,
    90,
    84
  ],
  "faceVertexIndices3": [
    2,
    3,
    4,
    5,
    1,
    2,
    6,
    3,
    7,
    4,
    8,
    9,
    5,
    6,
    10,
    11,
    7,
    12,
    13,
    8,
    10,
    9,
    12,
    11,
    16,
    17,
    15,
    18,
    19,
    20,
    12,
    13,
    16,
    10,
    11,
    21,
    22,
    23,
    18,
    24,
    25,
    19,
    22,
    21,
    20,
    16,
    24,
    23,
    28,
    29,
    30,
    27,
    28,
    31,
    29,
    32,
    33,
    34,
    35,
    30,
    36,
    37,
    27,
    32,
    31,
    25,
    24,
    37,
    39,
    40,
    41,
    32,
    42,
    43,
    33,
    44,
    45,
    46,
    47,
    34,
    41,
    48,
    49,
    35,
    50,
    40,
    51,
    36,
    52,
    53,
    54,
    38,
    55,
    56,
    39,
    57,
    58,
    59,
    51,
    40,
    36,
    38,
    60,
    61,
    62,
    53,
    63,
    64,
    54,
    65,
    55,
    66,
    56,
    63,
    62,
    57,
    61,
    67,
    58,
    68,
    59,
    69,
    70,
    51,
    60,
    71,
    61,
    67,
    69,
    68,
    66,
    72,
    63,
    64,
    25,
    31,
    28,
    47,
    74,
    75,
    42,
    41,
    43,
    33,
    76,
    77,
    78,
    45,
    79,
    80,
    46,
    81,
    73,
    82,
    74,
    83,
    84,
    75,
    85,
    86,
    42,
    87,
    88,
    43,
    76,
    89,
    77,
    78,
    80,
    79,
    87,
    83,
    82,
    88,
    81,
    89,
    80,
    90,
    86,
    40,
    41,
    48,
    92,
    93,
    49,
    94,
    50,
    95,
    91,
    92,
    70,
    69,
    71,
    90,
    84,
    83
  ],
  "faceRenderPriorities": [],
  "priority": 10,
  "faceAlphas": [
    96,
    96,
    96,
    96,
    96,
    96,
    96,
    96,
    96,
    96,
    96,
    96,
    96,
    96,
    96,
    96,
    96,
    96,
    96,
    96,
    96,
    96,
    96,
    96,
    96,
    96,
    96,
    96,
    96,
    96,
    96,
    96,
    96,
    96,
    96,
    96,
    96,
    96,
    96,
    96,
    96,
    96,
    96,
    96,
    96,
    96,
    96,
    96,
    96,
    0,
    0,
    0,
    0,
    0,
    0,
    0,
    0,
    0,
    0,
    0,
    0,
    0,
    0,
    0,
    0,
    96,
    96,
    0,
    0,
    0,
    0,
    0,
    0,
    0,
    0,
    96,
    96,
    96,
    96,
    0,
    0,
    0,
    0,
    0,
    0,
    0,
    0,
    0,
    96,
    96,
    96,
    96,
    96,
    96,
    96,
    96,
    96,
    96,
    96,
    0,
    0,
    0,
    96,
    96,
    96,
    96,
    96,
    96,
    96,
    96,
    96,
    96,
    96,
    96,
    96,
    96,
    96,
    96,
    96,
    96,
    96,
    96,
    96,
    96,
    96,
    96,
    96,
    96,
    96,
    96,
    96,
    96,
    96,
    96,
    96,
    96,
    96,
    96,
    96,
    96,
    96,
    0,
    0,
    0,
    96,
    96,
    96,
    96,
    96,
    96,
    96,
    96,
    96,
    96,
    96,
    96,
    96,
    96,
    96,
    96,
    96,
    96,
    96,
    96,
    96,
    96,
    96,
    96,
    96,
    96,
    96,
    96,
    96,
    96,
    96,
    96,
    96,
    96,
    96,
    0,
    0,
    0,
    0,
    0,
    0,
    0,
    0,
    0,
    0,
    0,
    96,
    96,
    96,
    96,
    96,
    96
  ],
  "faceTextures": [],
  "texIndices1": [],
  "texIndices2": [],
  "texIndices3": [],
  "faceColors": [
    111,
    111,
    111,
    111,
    111,
    111,
    111,
    111,
    111,
    111,
    111,
    111,
    111,
    111,
    111,
    111,
    111,
    111,
    111,
    111,
    111,
    111,
    111,
    111,
    111,
    111,
    111,
    111,
    111,
    111,
    111,
    111,
    111,
    111,
    111,
    111,
    111,
    111,
    111,
    111,
    111,
    111,
    111,
    111,
    111,
    111,
    111,
    111,
    111,
    274,
    274,
    274,
    274,
    274,
    274,
    274,
    274,
    274,
    274,
    274,
    274,
    274,
    274,
    274,
    274,
    111,
    111,
    274,
    274,
    274,
    274,
    274,
    274,
    274,
    274,
    111,
    111,
    111,
    111,
    274,
    274,
    274,
    274,
    274,
    274,
    274,
    274,
    274,
    111,
    111,
    111,
    111,
    111,
    111,
    111,
    111,
    111,
    111,
    111,
    274,
    274,
    274,
    111,
    127,
    127,
    127,
    127,
    127,
    111,
    111,
    111,
    111,
    111,
    127,
    127,
    127,
    127,
    127,
    111,
    111,
    111,
    111,
    111,
    111,
    111,
    127,
    127,
    127,
    127,
    111,
    111,
    127,
    127,
    127,
    111,
    111,
    111,
    111,
    111,
    111,
    111,
    274,
    274,
    274,
    111,
    111,
    111,
    111,
    127,
    127,
    127,
    127,
    127,
    127,
    127,
    127,
    127,
    111,
    111,
    111,
    111,
    111,
    111,
    111,
    111,
    111,
    111,
    111,
    127,
    127,
    111,
    127,
    127,
    127,
    127,
    127,
    127,
    111,
    111,
    274,
    274,
    274,
    6449,
    6449,
    6449,
    6449,
    6449,
    6449,
    6449,
    6449,
    127,
    127,
    127,
    127,
    127,
    127
  ],
  "textureRenderTypes": [],
  "vertexGroups": [],
  "position": {
    "x": 0,
    "y": 0,
    "z": 0
  },
  "rev229": true,
  "faceZOffsets": [
    0,
    0,
    0,
    0,
    0,
    0,
    0,
    0,
    0,
    0,
    0,
    0,
    0,
    0,
    0,
    0,
    0,
    0,
    0,
    0,
    0,
    0,
    0,
    0,
    0,
    0,
    0,
    0,
    0,
    0,
    0,
    0,
    0,
    0,
    0,
    0,
    0,
    0,
    1,
    1,
    0,
    0,
    0,
    0,
    0,
    0,
    0,
    0,
    0,
    0,
    0,
    0,
    0,
    0,
    0,
    0,
    0,
    0,
    0,
    0,
    0,
    0,
    0,
    0,
    0,
    0,
    0,
    0,
    0,
    0,
    0,
    0,
    0,
    0,
    0,
    0,
    0,
    0,
    0,
    0,
    0,
    0,
    0,
    0,
    0,
    0,
    0,
    0,
    0,
    0,
    0,
    0,
    0,
    0,
    0,
    0,
    0,
    0,
    0,
    0,
    0,
    0,
    0,
    0,
    0,
    0,
    0,
    0,
    0,
    0,
    0,
    0,
    0,
    0,
    0,
    0,
    0,
    0,
    0,
    0,
    0,
    0,
    0,
    0,
    0,
    0,
    0,
    0,
    0,
    0,
    0,
    0,
    0,
    0,
    0,
    0,
    0,
    0,
    0,
    0,
    0,
    0,
    0,
    0,
    0,
    0,
    0,
    0,
    0,
    0,
    0,
    0,
    0,
    0,
    0,
    0,
    0,
    0,
    0,
    0,
    0,
    0,
    0,
    0,
    0,
    0,
    0,
    0,
    0,
    0,
    0,
    0,
    0,
    0,
    0,
    0,
    0,
    0,
    0,
    0,
    0,
    0,
    0,
    0,
    0,
    0,
    0,
    0,
    0,
    0,
    0,
    0,
    0,
    0,
    0,
    0
  ],
  "vertexNormals": [
    {
      "x": -123.81699346405225,
      "y": 256,
      "z": 165.6470588235294,
      "magnitude": 5
    },
    {
      "x": -61.90849673202612,
      "y": -256,
      "z": 82.8235294117647,
      "magnitude": 3
    },
    {
      "x": 526.3417366946778,
      "y": -499.8095238095238,
      "z": 738.5994397759104,
      "magnitude": 5
    },
    {
      "x": 738.5994397759104,
      "y": 499.8095238095238,
      "z": 661.8711484593837,
      "magnitude": 5
    },
    {
      "x": -273.2698412698412,
      "y": 755.8095238095239,
      "z": -764.952380952381,
      "magnitude": 6
    },
    {
      "x": -665.3968253968254,
      "y": -755.8095238095239,
      "z": -387.04761904761904,
      "magnitude": 6
    },
    {
      "x": 643.047619047619,
      "y": -1011.8095238095239,
      "z": 636.952380952381,
      "magnitude": 7
    },
    {
      "x": 892.952380952381,
      "y": 1011.8095238095239,
      "z": 131.04761904761904,
      "magnitude": 7
    },
    {
      "x": -362.66666666666663,
      "y": 682.6666666666666,
      "z": -746.6666666666666,
      "magnitude": 5
    },
    {
      "x": -490.66666666666663,
      "y": -512,
      "z": -704,
      "magnitude": 5
    },
    {
      "x": -341.3333333333333,
      "y": -341.33333333333337,
      "z": -682.6666666666666,
      "magnitude": 6
    },
    {
      "x": 768,
      "y": -768,
      "z": 256,
      "magnitude": 6
    },
    {
      "x": 768,
      "y": 768,
      "z": 512,
      "magnitude": 6
    },
    {
      "x": -85.33333333333333,
      "y": 1450.6666666666665,
      "z": -682.6666666666666,
      "magnitude": 6
    },
    {
      "x": 256,
      "y": -512,
      "z": 768,
      "magnitude": 5
    },
    {
      "x": -320,
      "y": 896,
      "z": 1002.6666666666666,
      "magnitude": 6
    },
    {
      "x": -170.66666666666666,
      "y": -170.66666666666666,
      "z": -341.33333333333337,
      "magnitude": 7
    },
    {
      "x": -149.33333333333331,
      "y": -341.33333333333337,
      "z": 704,
      "magnitude": 7
    },
    {
      "x": -8.42105263157896,
      "y": 786.5263157894736,
      "z": 987.5087719298247,
      "magnitude": 6
    },
    {
      "x": -614.0952380952381,
      "y": 739.047619047619,
      "z": -7.619047619047606,
      "magnitude": 6
    },
    {
      "x": -518.0952380952381,
      "y": 963.0476190476192,
      "z": 152.38095238095235,
      "magnitude": 6
    },
    {
      "x": -390.0952380952381,
      "y": -60.95238095238095,
      "z": 24.38095238095238,
      "magnitude": 5
    },
    {
      "x": 128,
      "y": -512,
      "z": -768,
      "magnitude": 6
    },
    {
      "x": 384,
      "y": 0,
      "z": 128,
      "magnitude": 6
    },
    {
      "x": 236.91228070175436,
      "y": 71.85964912280701,
      "z": -409.8245614035087,
      "magnitude": 5
    },
    {
      "x": 311.57894736842104,
      "y": 402.52631578947364,
      "z": -868.4912280701755,
      "magnitude": 7
    },
    {
      "x": 8.533333333333331,
      "y": -256,
      "z": -136.53333333333336,
      "magnitude": 7
    },
    {
      "x": 329.9555555555555,
      "y": 512,
      "z": 96.71111111111108,
      "magnitude": 9
    },
    {
      "x": -366.9333333333334,
      "y": 0,
      "z": -273.0666666666666,
      "magnitude": 8
    },
    {
      "x": -597.3333333333334,
      "y": -1280,
      "z": -127.99999999999997,
      "magnitude": 8
    },
    {
      "x": 221.86666666666667,
      "y": -768,
      "z": 546.1333333333333,
      "magnitude": 6
    },
    {
      "x": -304.3555555555556,
      "y": 426.66666666666663,
      "z": -591.6444444444444,
      "magnitude": 6
    },
    {
      "x": -717.0058479532163,
      "y": 1250.5263157894738,
      "z": 431.812865497076,
      "magnitude": 8
    },
    {
      "x": -414.4761904761905,
      "y": -1280,
      "z": 353.5238095238095,
      "magnitude": 9
    },
    {
      "x": -219.42857142857142,
      "y": -1024,
      "z": -536.3809523809523,
      "magnitude": 7
    },
    {
      "x": 359.26050420168065,
      "y": -1536,
      "z": -132.94789915966385,
      "magnitude": 8
    },
    {
      "x": -153.60000000000002,
      "y": -1280,
      "z": 543.6952380952381,
      "magnitude": 10
    },
    {
      "x": -539.0222222222222,
      "y": 1248,
      "z": 933.6888888888891,
      "magnitude": 8
    },
    {
      "x": -448.27031055900625,
      "y": 768,
      "z": 103.19503105590061,
      "magnitude": 7
    },
    {
      "x": 15.821118012422374,
      "y": 1235.8095238095239,
      "z": -20.843064182194638,
      "magnitude": 10
    },
    {
      "x": 277.33333333333337,
      "y": 736,
      "z": 142.93333333333334,
      "magnitude": 7
    },
    {
      "x": -189.7142857142857,
      "y": 1264,
      "z": -261.33333333333337,
      "magnitude": 8
    },
    {
      "x": 38.12731829573933,
      "y": 1221.0526315789473,
      "z": 303.20601503759394,
      "magnitude": 9
    },
    {
      "x": -358.57109440267334,
      "y": 741.0526315789473,
      "z": 216.75522138680037,
      "magnitude": 8
    },
    {
      "x": 650.268131868132,
      "y": -768,
      "z": 572.4835164835165,
      "magnitude": 6
    },
    {
      "x": -255.25247512344288,
      "y": -1474.5232974910396,
      "z": -76.15289370128079,
      "magnitude": 6
    },
    {
      "x": -315.73333333333335,
      "y": -1493.3333333333333,
      "z": -150.75555555555553,
      "magnitude": 6
    },
    {
      "x": 75.5809523809524,
      "y": -1280,
      "z": -621.7142857142858,
      "magnitude": 10
    },
    {
      "x": -664.9729359369647,
      "y": 768,
      "z": -492.7737652242738,
      "magnitude": 6
    },
    {
      "x": -505.06192505987906,
      "y": -910.6285714285714,
      "z": -565.3259958256166,
      "magnitude": 6
    },
    {
      "x": 527.061011764253,
      "y": -768,
      "z": 538.2494769957417,
      "magnitude": 6
    },
    {
      "x": 253.56190476190477,
      "y": -1280,
      "z": -570.5142857142857,
      "magnitude": 9
    },
    {
      "x": 241.77777777777777,
      "y": -1521.7777777777778,
      "z": 256,
      "magnitude": 6
    },
    {
      "x": 175.28427128427128,
      "y": -1469.3587301587304,
      "z": 328.8103896103896,
      "magnitude": 6
    },
    {
      "x": -624.6326118326118,
      "y": -768,
      "z": -588.8369408369408,
      "magnitude": 6
    },
    {
      "x": -323.7862413609782,
      "y": 768,
      "z": -427.49686337054754,
      "magnitude": 5
    },
    {
      "x": -59.76398592388898,
      "y": 1764.7507002801121,
      "z": 166.9591472286855,
      "magnitude": 7
    },
    {
      "x": 29.400560224089645,
      "y": 1508.7507002801121,
      "z": 249.18767507002804,
      "magnitude": 6
    },
    {
      "x": -386.0078431372549,
      "y": 768,
      "z": -344.47058823529414,
      "magnitude": 5
    },
    {
      "x": -604.9206636500753,
      "y": -768,
      "z": -593.0859728506788,
      "magnitude": 6
    },
    {
      "x": 266.03921568627453,
      "y": -1249.8823529411766,
      "z": 205.80392156862746,
      "magnitude": 5
    },
    {
      "x": 527.0588235294118,
      "y": -15.058823529411768,
      "z": 436.7058823529412,
      "magnitude": 6
    },
    {
      "x": 229.58730158730157,
      "y": 32.507936507936506,
      "z": 390.0952380952381,
      "magnitude": 6
    },
    {
      "x": 255.7108520827686,
      "y": 4.327966025119736,
      "z": 412.0681666214873,
      "magnitude": 6
    },
    {
      "x": -51.58787878787879,
      "y": -477.8666666666667,
      "z": 129.93939393939394,
      "magnitude": 6
    },
    {
      "x": -229.4949494949495,
      "y": 256,
      "z": -239.19191919191917,
      "magnitude": 4
    },
    {
      "x": 106.58458186176154,
      "y": 1487.9089184060722,
      "z": 181.59525707489354,
      "magnitude": 6
    },
    {
      "x": 297.02868937048504,
      "y": 1485.671826625387,
      "z": 98.72555899552802,
      "magnitude": 6
    },
    {
      "x": -270.8078431372549,
      "y": 256,
      "z": -213.62614379084968,
      "magnitude": 4
    },
    {
      "x": 75.39093888567572,
      "y": -20.21052631578948,
      "z": -80.18898528372213,
      "magnitude": 6
    },
    {
      "x": 214.47370462354982,
      "y": -1500.7306501547987,
      "z": 67.47554860000679,
      "magnitude": 6
    },
    {
      "x": 479.90092879256963,
      "y": 15.058823529411768,
      "z": 234.60061919504642,
      "magnitude": 6
    },
    {
      "x": 36.748387096774195,
      "y": 222.9677419354839,
      "z": 136.6709677419355,
      "magnitude": 3
    },
    {
      "x": -309.1692307692308,
      "y": -1240.6153846153845,
      "z": -317.04615384615386,
      "magnitude": 5
    },
    {
      "x": -195.93846153846152,
      "y": -1406.0307692307692,
      "z": -442.09230769230766,
      "magnitude": 6
    },
    {
      "x": 558.9333333333333,
      "y": -768,
      "z": 627.2,
      "magnitude": 6
    },
    {
      "x": 443.8637494637495,
      "y": 768,
      "z": 284.85834405834413,
      "magnitude": 5
    },
    {
      "x": 309.0066066066066,
      "y": 256,
      "z": 241.20120120120123,
      "magnitude": 4
    },
    {
      "x": -66.40066446962999,
      "y": -44.13793103448279,
      "z": 87.41848190124053,
      "magnitude": 6
    },
    {
      "x": -131.62854349951124,
      "y": -222.9677419354839,
      "z": -34.03323558162268,
      "magnitude": 3
    },
    {
      "x": -597.9123470522803,
      "y": -2.5723396366332736,
      "z": -235.61428747991596,
      "magnitude": 6
    },
    {
      "x": -436.62222222222226,
      "y": -19.911111111111154,
      "z": -298.6666666666667,
      "magnitude": 6
    },
    {
      "x": -556.3076923076924,
      "y": -24.61538461538464,
      "z": -541.5384615384614,
      "magnitude": 6
    },
    {
      "x": -348.9476923076923,
      "y": -39.38461538461536,
      "z": -710.4984615384615,
      "magnitude": 6
    },
    {
      "x": 48.872727272727275,
      "y": -460.79999999999995,
      "z": -141.9636363636364,
      "magnitude": 6
    },
    {
      "x": 246.35844155844157,
      "y": 256,
      "z": 223.75064935064935,
      "magnitude": 4
    },
    {
      "x": 342.55238095238093,
      "y": 768,
      "z": 391.31428571428575,
      "magnitude": 5
    },
    {
      "x": -429.53846153846155,
      "y": 1377.2307692307693,
      "z": -195.69230769230768,
      "magnitude": 6
    },
    {
      "x": -282.1239766081871,
      "y": 1698.5263157894738,
      "z": 61.5391812865497,
      "magnitude": 7
    },
    {
      "x": -217.3014393704049,
      "y": 1457.728735632184,
      "z": -86.909143626385,
      "magnitude": 6
    },
    {
      "x": -85.85078921078922,
      "y": 1445.4153846153847,
      "z": -300.65550449550454,
      "magnitude": 6
    },
    {
      "x": 499.3757629512828,
      "y": 615.4520547945206,
      "z": 511.40985580925917,
      "magnitude": 6
    },
    {
      "x": 155.0035806970862,
      "y": 359.45205479452056,
      "z": 134.83709470779542,
      "magnitude": 3
    },
    {
      "x": -349.85789653991094,
      "y": 113.37142857142857,
      "z": -316.6082290817592,
      "magnitude": 3
    },
    {
      "x": -161.3423495802848,
      "y": -654.6285714285714,
      "z": -138.7336583273531,
      "magnitude": 3
    },
    {
      "x": 343.52802488675434,
      "y": -408.54794520547944,
      "z": 310.4914230654143,
      "magnitude": 3
    },
    {
      "x": 108.36691729323309,
      "y": -235.78947368421052,
      "z": 19.05563909774436,
      "magnitude": 3
    },
    {
      "x": -48.64,
      "y": 204.8,
      "z": -156.16000000000003,
      "magnitude": 3
    }
  ],
  "faceTextureUCoordinates": [
    [
      0,
      1,
      0
    ],
    [
      0,
      1,
      0
    ],
    [
      0,
      1,
      0
    ],
    [
      0,
      1,
      0
    ],
    [
      0,
      1,
      0
    ],
    [
      0,
      1,
      0
    ],
    [
      0,
      1,
      0
    ],
    [
      0,
      1,
      0
    ],
    [
      0,
      1,
      0
    ],
    [
      0,
      1,
      0
    ],
    [
      0,
      1,
      0
    ],
    [
      0,
      1,
      0
    ],
    [
      0,
      1,
      0
    ],
    [
      0,
      1,
      0
    ],
    [
      0,
      1,
      0
    ],
    [
      0,
      1,
      0
    ],
    [
      0,
      1,
      0
    ],
    [
      0,
      1,
      0
    ],
    [
      0,
      1,
      0
    ],
    [
      0,
      1,
      0
    ],
    [
      0,
      1,
      0
    ],
    [
      0,
      1,
      0
    ],
    [
      0,
      1,
      0
    ],
    [
      0,
      1,
      0
    ],
    [
      0,
      1,
      0
    ],
    [
      0,
      1,
      0
    ],
    [
      0,
      1,
      0
    ],
    [
      0,
      1,
      0
    ],
    [
      0,
      1,
      0
    ],
    [
      0,
      1,
      0
    ],
    [
      0,
      1,
      0
    ],
    [
      0,
      1,
      0
    ],
    [
      0,
      1,
      0
    ],
    [
      0,
      1,
      0
    ],
    [
      0,
      1,
      0
    ],
    [
      0,
      1,
      0
    ],
    [
      0,
      1,
      0
    ],
    [
      0,
      1,
      0
    ],
    [
      0,
      1,
      0
    ],
    [
      0,
      1,
      0
    ],
    [
      0,
      1,
      0
    ],
    [
      0,
      1,
      0
    ],
    [
      0,
      1,
      0
    ],
    [
      0,
      1,
      0
    ],
    [
      0,
      1,
      0
    ],
    [
      0,
      1,
      0
    ],
    [
      0,
      1,
      0
    ],
    [
      0,
      1,
      0
    ],
    [
      0,
      1,
      0
    ],
    [
      0,
      1,
      0
    ],
    [
      0,
      1,
      0
    ],
    [
      0,
      1,
      0
    ],
    [
      0,
      1,
      0
    ],
    [
      0,
      1,
      0
    ],
    [
      0,
      1,
      0
    ],
    [
      0,
      1,
      0
    ],
    [
      0,
      1,
      0
    ],
    [
      0,
      1,
      0
    ],
    [
      0,
      1,
      0
    ],
    [
      0,
      1,
      0
    ],
    [
      0,
      1,
      0
    ],
    [
      0,
      1,
      0
    ],
    [
      0,
      1,
      0
    ],
    [
      0,
      1,
      0
    ],
    [
      0,
      1,
      0
    ],
    [
      0,
      1,
      0
    ],
    [
      0,
      1,
      0
    ],
    [
      0,
      1,
      0
    ],
    [
      0,
      1,
      0
    ],
    [
      0,
      1,
      0
    ],
    [
      0,
      1,
      0
    ],
    [
      0,
      1,
      0
    ],
    [
      0,
      1,
      0
    ],
    [
      0,
      1,
      0
    ],
    [
      0,
      1,
      0
    ],
    [
      0,
      1,
      0
    ],
    [
      0,
      1,
      0
    ],
    [
      0,
      1,
      0
    ],
    [
      0,
      1,
      0
    ],
    [
      0,
      1,
      0
    ],
    [
      0,
      1,
      0
    ],
    [
      0,
      1,
      0
    ],
    [
      0,
      1,
      0
    ],
    [
      0,
      1,
      0
    ],
    [
      0,
      1,
      0
    ],
    [
      0,
      1,
      0
    ],
    [
      0,
      1,
      0
    ],
    [
      0,
      1,
      0
    ],
    [
      0,
      1,
      0
    ],
    [
      0,
      1,
      0
    ],
    [
      0,
      1,
      0
    ],
    [
      0,
      1,
      0
    ],
    [
      0,
      1,
      0
    ],
    [
      0,
      1,
      0
    ],
    [
      0,
      1,
      0
    ],
    [
      0,
      1,
      0
    ],
    [
      0,
      1,
      0
    ],
    [
      0,
      1,
      0
    ],
    [
      0,
      1,
      0
    ],
    [
      0,
      1,
      0
    ],
    [
      0,
      1,
      0
    ],
    [
      0,
      1,
      0
    ],
    [
      0,
      1,
      0
    ],
    [
      0,
      1,
      0
    ],
    [
      0,
      1,
      0
    ],
    [
      0,
      1,
      0
    ],
    [
      0,
      1,
      0
    ],
    [
      0,
      1,
      0
    ],
    [
      0,
      1,
      0
    ],
    [
      0,
      1,
      0
    ],
    [
      0,
      1,
      0
    ],
    [
      0,
      1,
      0
    ],
    [
      0,
      1,
      0
    ],
    [
      0,
      1,
      0
    ],
    [
      0,
      1,
      0
    ],
    [
      0,
      1,
      0
    ],
    [
      0,
      1,
      0
    ],
    [
      0,
      1,
      0
    ],
    [
      0,
      1,
      0
    ],
    [
      0,
      1,
      0
    ],
    [
      0,
      1,
      0
    ],
    [
      0,
      1,
      0
    ],
    [
      0,
      1,
      0
    ],
    [
      0,
      1,
      0
    ],
    [
      0,
      1,
      0
    ],
    [
      0,
      1,
      0
    ],
    [
      0,
      1,
      0
    ],
    [
      0,
      1,
      0
    ],
    [
      0,
      1,
      0
    ],
    [
      0,
      1,
      0
    ],
    [
      0,
      1,
      0
    ],
    [
      0,
      1,
      0
    ],
    [
      0,
      1,
      0
    ],
    [
      0,
      1,
      0
    ],
    [
      0,
      1,
      0
    ],
    [
      0,
      1,
      0
    ],
    [
      0,
      1,
      0
    ],
    [
      0,
      1,
      0
    ],
    [
      0,
      1,
      0
    ],
    [
      0,
      1,
      0
    ],
    [
      0,
      1,
      0
    ],
    [
      0,
      1,
      0
    ],
    [
      0,
      1,
      0
    ],
    [
      0,
      1,
      0
    ],
    [
      0,
      1,
      0
    ],
    [
      0,
      1,
      0
    ],
    [
      0,
      1,
      0
    ],
    [
      0,
      1,
      0
    ],
    [
      0,
      1,
      0
    ],
    [
      0,
      1,
      0
    ],
    [
      0,
      1,
      0
    ],
    [
      0,
      1,
      0
    ],
    [
      0,
      1,
      0
    ],
    [
      0,
      1,
      0
    ],
    [
      0,
      1,
      0
    ],
    [
      0,
      1,
      0
    ],
    [
      0,
      1,
      0
    ],
    [
      0,
      1,
      0
    ],
    [
      0,
      1,
      0
    ],
    [
      0,
      1,
      0
    ],
    [
      0,
      1,
      0
    ],
    [
      0,
      1,
      0
    ],
    [
      0,
      1,
      0
    ],
    [
      0,
      1,
      0
    ],
    [
      0,
      1,
      0
    ],
    [
      0,
      1,
      0
    ],
    [
      0,
      1,
      0
    ],
    [
      0,
      1,
      0
    ],
    [
      0,
      1,
      0
    ],
    [
      0,
      1,
      0
    ],
    [
      0,
      1,
      0
    ],
    [
      0,
      1,
      0
    ],
    [
      0,
      1,
      0
    ],
    [
      0,
      1,
      0
    ],
    [
      0,
      1,
      0
    ],
    [
      0,
      1,
      0
    ],
    [
      0,
      1,
      0
    ],
    [
      0,
      1,
      0
    ],
    [
      0,
      1,
      0
    ],
    [
      0,
      1,
      0
    ],
    [
      0,
      1,
      0
    ],
    [
      0,
      1,
      0
    ],
    [
      0,
      1,
      0
    ],
    [
      0,
      1,
      0
    ],
    [
      0,
      1,
      0
    ],
    [
      0,
      1,
      0
    ],
    [
      0,
      1,
      0
    ],
    [
      0,
      1,
      0
    ],
    [
      0,
      1,
      0
    ],
    [
      0,
      1,
      0
    ],
    [
      0,
      1,
      0
    ],
    [
      0,
      1,
      0
    ],
    [
      0,
      1,
      0
    ],
    [
      0,
      1,
      0
    ],
    [
      0,
      1,
      0
    ],
    [
      0,
      1,
      0
    ]
  ],
  "faceTextureVCoordinates": [
    [
      0,
      0,
      1
    ],
    [
      0,
      0,
      1
    ],
    [
      0,
      0,
      1
    ],
    [
      0,
      0,
      1
    ],
    [
      0,
      0,
      1
    ],
    [
      0,
      0,
      1
    ],
    [
      0,
      0,
      1
    ],
    [
      0,
      0,
      1
    ],
    [
      0,
      0,
      1
    ],
    [
      0,
      0,
      1
    ],
    [
      0,
      0,
      1
    ],
    [
      0,
      0,
      1
    ],
    [
      0,
      0,
      1
    ],
    [
      0,
      0,
      1
    ],
    [
      0,
      0,
      1
    ],
    [
      0,
      0,
      1
    ],
    [
      0,
      0,
      1
    ],
    [
      0,
      0,
      1
    ],
    [
      0,
      0,
      1
    ],
    [
      0,
      0,
      1
    ],
    [
      0,
      0,
      1
    ],
    [
      0,
      0,
      1
    ],
    [
      0,
      0,
      1
    ],
    [
      0,
      0,
      1
    ],
    [
      0,
      0,
      1
    ],
    [
      0,
      0,
      1
    ],
    [
      0,
      0,
      1
    ],
    [
      0,
      0,
      1
    ],
    [
      0,
      0,
      1
    ],
    [
      0,
      0,
      1
    ],
    [
      0,
      0,
      1
    ],
    [
      0,
      0,
      1
    ],
    [
      0,
      0,
      1
    ],
    [
      0,
      0,
      1
    ],
    [
      0,
      0,
      1
    ],
    [
      0,
      0,
      1
    ],
    [
      0,
      0,
      1
    ],
    [
      0,
      0,
      1
    ],
    [
      0,
      0,
      1
    ],
    [
      0,
      0,
      1
    ],
    [
      0,
      0,
      1
    ],
    [
      0,
      0,
      1
    ],
    [
      0,
      0,
      1
    ],
    [
      0,
      0,
      1
    ],
    [
      0,
      0,
      1
    ],
    [
      0,
      0,
      1
    ],
    [
      0,
      0,
      1
    ],
    [
      0,
      0,
      1
    ],
    [
      0,
      0,
      1
    ],
    [
      0,
      0,
      1
    ],
    [
      0,
      0,
      1
    ],
    [
      0,
      0,
      1
    ],
    [
      0,
      0,
      1
    ],
    [
      0,
      0,
      1
    ],
    [
      0,
      0,
      1
    ],
    [
      0,
      0,
      1
    ],
    [
      0,
      0,
      1
    ],
    [
      0,
      0,
      1
    ],
    [
      0,
      0,
      1
    ],
    [
      0,
      0,
      1
    ],
    [
      0,
      0,
      1
    ],
    [
      0,
      0,
      1
    ],
    [
      0,
      0,
      1
    ],
    [
      0,
      0,
      1
    ],
    [
      0,
      0,
      1
    ],
    [
      0,
      0,
      1
    ],
    [
      0,
      0,
      1
    ],
    [
      0,
      0,
      1
    ],
    [
      0,
      0,
      1
    ],
    [
      0,
      0,
      1
    ],
    [
      0,
      0,
      1
    ],
    [
      0,
      0,
      1
    ],
    [
      0,
      0,
      1
    ],
    [
      0,
      0,
      1
    ],
    [
      0,
      0,
      1
    ],
    [
      0,
      0,
      1
    ],
    [
      0,
      0,
      1
    ],
    [
      0,
      0,
      1
    ],
    [
      0,
      0,
      1
    ],
    [
      0,
      0,
      1
    ],
    [
      0,
      0,
      1
    ],
    [
      0,
      0,
      1
    ],
    [
      0,
      0,
      1
    ],
    [
      0,
      0,
      1
    ],
    [
      0,
      0,
      1
    ],
    [
      0,
      0,
      1
    ],
    [
      0,
      0,
      1
    ],
    [
      0,
      0,
      1
    ],
    [
      0,
      0,
      1
    ],
    [
      0,
      0,
      1
    ],
    [
      0,
      0,
      1
    ],
    [
      0,
      0,
      1
    ],
    [
      0,
      0,
      1
    ],
    [
      0,
      0,
      1
    ],
    [
      0,
      0,
      1
    ],
    [
      0,
      0,
      1
    ],
    [
      0,
      0,
      1
    ],
    [
      0,
      0,
      1
    ],
    [
      0,
      0,
      1
    ],
    [
      0,
      0,
      1
    ],
    [
      0,
      0,
      1
    ],
    [
      0,
      0,
      1
    ],
    [
      0,
      0,
      1
    ],
    [
      0,
      0,
      1
    ],
    [
      0,
      0,
      1
    ],
    [
      0,
      0,
      1
    ],
    [
      0,
      0,
      1
    ],
    [
      0,
      0,
      1
    ],
    [
      0,
      0,
      1
    ],
    [
      0,
      0,
      1
    ],
    [
      0,
      0,
      1
    ],
    [
      0,
      0,
      1
    ],
    [
      0,
      0,
      1
    ],
    [
      0,
      0,
      1
    ],
    [
      0,
      0,
      1
    ],
    [
      0,
      0,
      1
    ],
    [
      0,
      0,
      1
    ],
    [
      0,
      0,
      1
    ],
    [
      0,
      0,
      1
    ],
    [
      0,
      0,
      1
    ],
    [
      0,
      0,
      1
    ],
    [
      0,
      0,
      1
    ],
    [
      0,
      0,
      1
    ],
    [
      0,
      0,
      1
    ],
    [
      0,
      0,
      1
    ],
    [
      0,
      0,
      1
    ],
    [
      0,
      0,
      1
    ],
    [
      0,
      0,
      1
    ],
    [
      0,
      0,
      1
    ],
    [
      0,
      0,
      1
    ],
    [
      0,
      0,
      1
    ],
    [
      0,
      0,
      1
    ],
    [
      0,
      0,
      1
    ],
    [
      0,
      0,
      1
    ],
    [
      0,
      0,
      1
    ],
    [
      0,
      0,
      1
    ],
    [
      0,
      0,
      1
    ],
    [
      0,
      0,
      1
    ],
    [
      0,
      0,
      1
    ],
    [
      0,
      0,
      1
    ],
    [
      0,
      0,
      1
    ],
    [
      0,
      0,
      1
    ],
    [
      0,
      0,
      1
    ],
    [
      0,
      0,
      1
    ],
    [
      0,
      0,
      1
    ],
    [
      0,
      0,
      1
    ],
    [
      0,
      0,
      1
    ],
    [
      0,
      0,
      1
    ],
    [
      0,
      0,
      1
    ],
    [
      0,
      0,
      1
    ],
    [
      0,
      0,
      1
    ],
    [
      0,
      0,
      1
    ],
    [
      0,
      0,
      1
    ],
    [
      0,
      0,
      1
    ],
    [
      0,
      0,
      1
    ],
    [
      0,
      0,
      1
    ],
    [
      0,
      0,
      1
    ],
    [
      0,
      0,
      1
    ],
    [
      0,
      0,
      1
    ],
    [
      0,
      0,
      1
    ],
    [
      0,
      0,
      1
    ],
    [
      0,
      0,
      1
    ],
    [
      0,
      0,
      1
    ],
    [
      0,
      0,
      1
    ],
    [
      0,
      0,
      1
    ],
    [
      0,
      0,
      1
    ],
    [
      0,
      0,
      1
    ],
    [
      0,
      0,
      1
    ],
    [
      0,
      0,
      1
    ],
    [
      0,
      0,
      1
    ],
    [
      0,
      0,
      1
    ],
    [
      0,
      0,
      1
    ],
    [
      0,
      0,
      1
    ],
    [
      0,
      0,
      1
    ],
    [
      0,
      0,
      1
    ],
    [
      0,
      0,
      1
    ],
    [
      0,
      0,
      1
    ],
    [
      0,
      0,
      1
    ],
    [
      0,
      0,
      1
    ],
    [
      0,
      0,
      1
    ],
    [
      0,
      0,
      1
    ],
    [
      0,
      0,
      1
    ],
    [
      0,
      0,
      1
    ],
    [
      0,
      0,
      1
    ],
    [
      0,
      0,
      1
    ],
    [
      0,
      0,
      1
    ],
    [
      0,
      0,
      1
    ],
    [
      0,
      0,
      1
    ],
    [
      0,
      0,
      1
    ],
    [
      0,
      0,
      1
    ],
    [
      0,
      0,
      1
    ],
    [
      0,
      0,
      1
    ],
    [
      0,
      0,
      1
    ],
    [
      0,
      0,
      1
    ],
    [
      0,
      0,
      1
    ],
    [
      0,
      0,
      1
    ]
  ]
}